{
  "project_info": {
    "project_number": "934604663898",
    "firebase_url": "https://hellocash-android.firebaseio.com",
    "project_id": "hellocash-android",
    "storage_bucket": "hellocash-android.appspot.com"
  },
  "client": [
    {
      "client_info": {
        "mobilesdk_app_id": "1:934604663898:android:1e1de1a3d0aec2f3",
        "android_client_info": {
          "package_name": "telvoterminal.telvo.com.terminal"
        }
      },
      "oauth_client": [
        {
          "client_id": "934604663898-75593297onaqbkvun6qfqc02sctntair.apps.googleusercontent.com",
          "client_type": 3
        }
      ],
      "api_key": [
        {
          "current_key": "AIzaSyDsvhaLkKj0hSzQBEAVG9BBa64BCWd_2pI"
        }
      ],
      "services": {
        "analytics_service": {
          "status": 1
        },
        "appinvite_service": {
          "status": 1,
          "other_platform_oauth_client": []
        },
        "ads_service": {
          "status": 2
        }
      }
    }
  ],
  "configuration_version": "1"
}